keystone_api/__init__.py
keystone_api/apps/__init__.py
keystone_api/apps/admin_utils/__init__.py
keystone_api/apps/admin_utils/management/__init__.py
keystone_api/apps/admin_utils/management/commands/__init__.py
keystone_api/apps/admin_utils/management/commands/clean.py
keystone_api/apps/admin_utils/management/commands/enable_autocomplete.py
keystone_api/apps/admin_utils/management/commands/genseeddata.py
keystone_api/apps/admin_utils/management/commands/keystone_autocomplete
keystone_api/apps/admin_utils/management/commands/quickstart.py
keystone_api/apps/allocations/__init__.py
keystone_api/apps/allocations/admin.py
keystone_api/apps/allocations/factories.py
keystone_api/apps/allocations/managers.py
keystone_api/apps/allocations/migrations/0001_initial.py
keystone_api/apps/allocations/migrations/0002_initial.py
keystone_api/apps/allocations/migrations/0003_remove_allocationrequest_approved_and_more.py
keystone_api/apps/allocations/migrations/0004_alter_allocation_awarded_alter_allocation_final_and_more.py
keystone_api/apps/allocations/migrations/0005_alter_allocationrequest_description.py
keystone_api/apps/allocations/migrations/0006_allocationrequest_assignees.py
keystone_api/apps/allocations/migrations/0007_alter_allocationrequestreview_reviewer.py
keystone_api/apps/allocations/migrations/0008_rename_date_modified_allocationrequestreview_last_modified_and_more.py
keystone_api/apps/allocations/migrations/0009_remove_allocationrequest_group.py
keystone_api/apps/allocations/migrations/0010_rename_file_data_attachment_path.py
keystone_api/apps/allocations/migrations/0011_rename_allocationrequestreview_allocationreview.py
keystone_api/apps/allocations/migrations/0012_allocationrequest_grants_and_more.py
keystone_api/apps/allocations/migrations/0013_remove_allocationreview_private_comments_and_more.py
keystone_api/apps/allocations/migrations/0014_rename_path_attachment_file_attachment_name.py
keystone_api/apps/allocations/migrations/0015_alter_attachment_name.py
keystone_api-0.7.4.dist-info/METADATA
keystone_api-0.7.4.dist-info/WHEEL
keystone_api-0.7.4.dist-info/entry_points.txt
keystone_api-0.7.4.dist-info/RECORD
