Metadata-Version: 2.4
Name: keystone-api
Version: 0.7.4
Summary: A REST API for managing user resource allocations on HPC systems.
Keywords: Better,HPC,keystone,api
Author: Better HPC LLC
Requires-Python: >=3.11,<4
Classifier: Environment :: Web Environment
Classifier: Framework :: Django
Classifier: Intended Audience :: Developers
Classifier: Intended Audience :: Information Technology
Classifier: Intended Audience :: System Administrators
Classifier: Natural Language :: English
Classifier: Operating System :: OS Independent
Classifier: Programming Language :: Python
Classifier: Topic :: Internet
Classifier: Topic :: Internet :: WWW/HTTP
Classifier: Topic :: Internet :: WWW/HTTP :: HTTP Servers
Classifier: Topic :: Software Development
Classifier: Topic :: Software Development :: Libraries
Classifier: Topic :: Software Development :: Libraries :: Application Frameworks
Classifier: Typing :: Typed
Provides-Extra: all
Provides-Extra: ldap
Provides-Extra: smtp
Provides-Extra: tests
Requires-Dist: Faker (==37.4.0)
Requires-Dist: aiosmtpd ; extra == "all"
Requires-Dist: aiosmtpd ; extra == "smtp"
Requires-Dist: coverage (==7.9.1)
Requires-Dist: coverage ; extra == "all"
Requires-Dist: coverage ; extra == "tests"
Requires-Dist: django (==5.2.6)
Requires-Dist: django-auditlog (==3.2.0)
Requires-Dist: django-auth-ldap ; extra == "all"
Requires-Dist: django-auth-ldap ; extra == "ldap"
Requires-Dist: django-celery-beat (==2.8.1)
Requires-Dist: django-celery-results (==2.6.0)
Requires-Dist: django-cors-headers (==4.7.0)
Requires-Dist: django-environ (==0.12.0)
Requires-Dist: django-filter (==25.1)
Requires-Dist: django-health-check (==3.20.0)
Requires-Dist: django-jazzmin (==3.0.1)
Requires-Dist: django-prometheus (==2.4.1)
Requires-Dist: djangorestframework (==3.16.0)
Requires-Dist: drf_spectacular[sidecar] (==0.28.0)
Requires-Dist: factory-boy (==3.3.3)
Requires-Dist: flower (==2.0.1)
Requires-Dist: iso4217 (>=1.14.20250512,<2.0.0)
Requires-Dist: jinja2 (==3.1.6)
Requires-Dist: pillow (==11.3.0)
Requires-Dist: psycopg2-binary (==2.9.10)
Requires-Dist: pyyaml (==6.0.2)
Requires-Dist: redis (==6.2.0)
Requires-Dist: servestatic (==3.1.0)
Requires-Dist: tqdm (==4.67.1)
Requires-Dist: uritemplate (==4.2.0)
Requires-Dist: uvicorn (==0.35.0)
